cyberutils/__init__.py
cyberutils/bash/__init__.py
cyberutils/bash/execution.py
cyberutils/contract/__init__.py
cyberutils/contract/execution.py
cyberutils/contract/instantiate.py
cyberutils/contract/query.py
cyberutils/graphql/__init__.py
cyberutils/graphql/execution.py
cyberutils/graphql/queries.py
cyberutils-0.0.6.dist-info/LICENSE
cyberutils-0.0.6.dist-info/METADATA
cyberutils-0.0.6.dist-info/WHEEL
cyberutils-0.0.6.dist-info/RECORD
